khcolors/__about__.py
khcolors/__init__.py
khcolors/__main__.py
khcolors/colors_util.py
khcolors/lib.py
khcolors-0.3.3.dist-info/METADATA
khcolors-0.3.3.dist-info/WHEEL
khcolors-0.3.3.dist-info/entry_points.txt
khcolors-0.3.3.dist-info/licenses/LICENSE.txt
khcolors-0.3.3.dist-info/RECORD
