Metadata-Version: 2.3
Name: khcolors
Version: 0.3.3
Summary: colour name choosing app, for rich and CSS4 palettes
Project-URL: Homepage, https://github.com/pykhaz/khcolors
Project-URL: Documentation, https://github.com/pykhaz/khcolors#readme
Project-URL: Issues, https://github.com/pykhaz/khcolors/issues
Project-URL: Source, https://github.com/pykhaz/khcolors
Author-email: pykhaz <pykhaz@o2.pl>
License-Expression: MIT
License-File: LICENSE.txt
Keywords: color,colour,css4,rich
Classifier: License :: OSI Approved :: MIT License
Classifier: Operating System :: OS Independent
Classifier: Programming Language :: Python :: 3
Requires-Python: >=3.8
Requires-Dist: matplotlib
Requires-Dist: pyperclip
Requires-Dist: rich
